[
    {
      "id": 1,
      "name": "Dan Cathy",
      "image": "https://i.ibb.co/N9L1JH2/s-l225-1.webp"
    },
    {
      "id": 2,
      "name": "Kristin Kullinger",
      "image": "https://i.ibb.co/hCjnryQ/s-l225-2.webp"
    },
    {
      "id": 3,
      "title": "Portia Pascal",
      "image": "https://i.ibb.co/ypP0yPt/s-l225-3.webp"
      
    },
    {
      "id": 4,
      "title": "Portia Pascal",
      "image": "https://i.ibb.co/YRWfdDs/s-l225-4.webp"
    },
    {
      "id": 5,
      "title": "Portia Pascal",
      "image": "https://i.ibb.co/7jwk65s/s-l225-5.webp"
    },
    {
      "id": 6,
      "title": "Portia Pascal",
      "image": "https://i.ibb.co/Drbwx64/s-l225-6.webp"
    },
    {
      "id": 7,
      "title": "Portia Pascal",
      "image": "https://i.ibb.co/W0jvswj/s-l225-7.webp"
    }
    
  ]